Workbook

Sheet 预算说明
A1: Visa Principal Acquiring 预算版 Excel
A3: 项目 | B3: 内容
A4: 来源文件 | B4: Projected Setup Cost Principal Acquiring070426.pdf
A5: 预算口径 | B5: 一次性基线 + 可选事件缓冲 + 年化经常性；交易级费率单独待补
A6: 建议用法 | B6: 先在“预算清单”确定适用项和是否纳入预算，再看“预算汇总”读当前预算与压力预算
A7: 关键字段 | B7: “是否适用”“是否纳入预算”可直接改；当前纳入预算和压力预算会自动汇总
A8: 注意 | B8: 带范围的项目默认采用建议预算和压力预算双口径；最新收费仍以 Visa Fee Schedule / Visa Online / MIDAS 正式回复为准

Sheet 预算清单
A1: ID | B1: 阶段/节点 | C1: 费用项 | D1: 费用分组 | E1: 预算口径 | F1: 是否必选 | G1: 是否适用 | H1: 是否纳入预算 | I1: 预算 Owner | J1: 预计发生时点 | K1: 金额下限(USD) | L1: 建议预算(USD) | M1: 压力预算(USD) | N1: 当前纳入预算(USD) | O1: 当前压力预算(USD) | P1: 备注/假设 | Q1: 待确认问题 | R1: 风险等级 | S1: 下一步动作
A2: LIC-01 | B2: Licensing kick-off | C2: Initial Service Fee | D2: Licensing | E2: 一次性基线 | F2: 是 | G2: 是 | H2: 是 | I2: Finance + Biz Owner + Legal/Compliance | J2: License 审批启动前 | K2: 75000 | L2: 75000 | M2: 75000 | N2: =IF(OR(G2="否",H2="否"),0,L2) -> 75000 | O2: =IF(OR(G2="否",H2="否"),0,M2) -> 75000 | P2: Principal 示例值 | Q2: 是否必须全额预付后才继续审批？ | R2: 高 | S2: 锁定付款前置条件与审批顺序
A3: LIC-02 | B3: Provisional BID assigned | C3: Numeric Licensing Fee | D3: Licensing | E3: 一次性基线 | F3: 是 | G3: 是 | H3: 是 | I3: Implementation Lead + Finance | J3: Provisional BID 批下后 / BIN 分配当月 | K3: 1000 | L3: 1000 | M3: 1000 | N3: =IF(OR(G3="否",H3="否"),0,L3) -> 1000 | O3: =IF(OR(G3="否",H3="否"),0,M3) -> 1000 | P3: 按示例 2 BIN 估算 | Q3: “当月开票”与“BIN go-live 后 billing timing”之间，实际扣款日是哪天？ | R3: 中 | S3: 确认 invoice date 与 actual collection date
A4: IMP-01 | B4: Implementation kick-off | C4: Project Management Fee | D4: Implementation | E4: 一次性基线 | F4: 是 | G4: 是 | H4: 是 | I4: PM/Implementation Lead + Finance | J4: Implementation 启动后 6 个月口径 | K4: 18000 | L4: 18000 | M4: 24000 | N4: =IF(OR(G4="否",H4="否"),0,L4) -> 18000 | O4: =IF(OR(G4="否",H4="否"),0,M4) -> 24000 | P4: 示例按 6 个月；压力口径按 8 个月 | Q4: 如果实施超过 6 个月，是否继续按月累计？ | R4: 高 | S4: 把 implementation 月数纳入预算基线
A5: CFG-01 | B5: CIQ 完成 + config request 提交 | C5: New Program Installation | D5: Configuration | E5: 一次性基线 | F5: 是 | G5: 是 | H5: 是 | I5: Implementation Lead | J5: CIQ 完成并提交配置请求后 | K5: 6000 | L5: 6000 | M5: 9000 | N5: =IF(OR(G5="否",H5="否"),0,L5) -> 6000 | O5: =IF(OR(G5="否",H5="否"),0,M5) -> 9000 | P5: 示例按 1 CIB + 1 PCR；压力口径预留额外 numeric | Q5: Settlement BIN 是否单独收费、是否已包含在当前示例里？ | R5: 中 | S5: 冻结架构后再提配置
A6: CFG-02 | B6: CIQ 完成 + config request 提交 | C6: Endpoint Certification Issuance Fee | D6: Configuration | E6: 一次性基线 | F6: 是 | G6: 是 | H6: 是 | I6: Network/Infra Lead + Implementation | J6: CIQ 完成并提交配置请求后 | K6: 550 | L6: 1100 | M6: 1100 | N6: =IF(OR(G6="否",H6="否"),0,L6) -> 1100 | O6: =IF(OR(G6="否",H6="否"),0,M6) -> 1100 | P6: 建议按 Prod + DR 两张证书预算 | Q6: Production 和 DR 是否各要一张证书？ | R6: 中 | S6: 确认 endpoint 与证书数量
A7: CFG-03 | B7: 证书请求 | C7: eCommerce Digital Certificate Issuance | D7: Configuration | E7: 一次性基线 | F7: 否 | G7: 待定 | H7: 否 | I7: 3DS Owner + Implementation | J7: 3DS 方案确定后 | K7: 550 | L7: 550 | M7: 1100 | N7: =IF(OR(G7="否",H7="否"),0,L7) -> 0 | O7: =IF(OR(G7="否",H7="否"),0,M7) -> 0 | P7: 仅自建/持有 3DS Server 时适用 | Q7: 如果使用第三方 3DS，证书费由谁承担？ | R7: 中 | S7: 确认 3DS 接入模式与证书 owner
A8: TST-01 | B8: Attended testing 完成 | C8: Attended Testing Fee | D8: Testing | E8: 一次性基线 | F8: 是 | G8: 是 | H8: 是 | I8: QA/Test Lead + Finance | J8: Attended testing 完成后 | K8: 12000 | L8: 12000 | M8: 16000 | N8: =IF(OR(G8="否",H8="否"),0,L8) -> 12000 | O8: =IF(OR(G8="否",H8="否"),0,M8) -> 16000 | P8: 示例按 12 小时；压力口径按 16 小时 | Q8: 超出预估小时数如何加收？是否按实际小时滚动？ | R8: 高 | S8: 锁定测试时长预估与排期
A9: TST-02 | B9: 提交 test card request | C9: Host Test Cards Package | D9: Testing | E9: 一次性基线 | F9: 否 | G9: 待定 | H9: 否 | I9: QA/Test Lead | J9: 测试准备阶段 | K9: 1000 | L9: 1000 | M9: 2000 | N9: =IF(OR(G9="否",H9="否"),0,L9) -> 0 | O9: =IF(OR(G9="否",H9="否"),0,M9) -> 0 | P9: 按 1 package 估算 | Q9: 一个 package 覆盖多少测试场景？需不需要重复买？ | R9: 低 | S9: 核对测试卡覆盖范围
A10: TST-03 | B10: 申请 VSTS access | C10: Visa Secure Test Suite (VSTS) | D10: Testing | E10: 一次性基线 | F10: 否 | G10: 待定 | H10: 否 | I10: 3DS Owner + QA | J10: 3DS 测试窗口开启时 | K10: 7500 | L10: 7500 | M10: 15000 | N10: =IF(OR(G10="否",H10="否"),0,L10) -> 0 | O10: =IF(OR(G10="否",H10="否"),0,M10) -> 0 | P10: 90 天订阅；压力口径按续费一次 | Q10: 如果 90 天测试未完成，是否续费同价？ | R10: 中 | S10: 按真实测试窗口申请订阅
A11: TST-04 | B11: IM 确认 proceed with VCX | C11: Visa Clearing Exchange License Fee | D11: Testing | E11: 一次性基线 | F11: 否 | G11: 待定 | H11: 否 | I11: Processing/Settlement Lead | J11: VCX 方案确认后 | K11: 8000 | L11: 8000 | M11: 8000 | N11: =IF(OR(G11="否",H11="否"),0,L11) -> 0 | O11: =IF(OR(G11="否",H11="否"),0,M11) -> 0 | P11: 仅需 VCX 时适用 | Q11: 如果第三方 processor 已覆盖，是否可完全不买？ | R11: 中 | S11: 比较自建与第三方 processor 成本
A12: TST-05 | B12: 提交 VTS 工具申请表 | C12: VisaNet Test System – System License Fee | D12: Testing | E12: 一次性基线 | F12: 否 | G12: 待定 | H12: 否 | I12: QA/Test Lead | J12: Host testing 工具申请后 | K12: 5000 | L12: 5000 | M12: 5000 | N12: =IF(OR(G12="否",H12="否"),0,L12) -> 0 | O12: =IF(OR(G12="否",H12="否"),0,M12) -> 0 | P12: 按单次系统许可证估算 | Q12: 是一次买断还是本项目一次性授权？ | R12: 中 | S12: 确认授权性质与复用范围
A13: ACC-01 | B13: 全部 testing + certification 完成 | C13: Visa Cloud Connect Access Fee / New EAS Installation Fee | D13: Access | E13: 一次性基线 | F13: 否 | G13: 待定 | H13: 否 | I13: Infra/Network Lead + Finance | J13: Endpoint activation 时 | K13: 20000 | L13: 20000 | M13: 20000 | N13: =IF(OR(G13="否",H13="否"),0,L13) -> 0 | O13: =IF(OR(G13="否",H13="否"),0,M13) -> 0 | P13: 示例按 1 Prod + 1 DR endpoint | Q13: 1 Production + 1 DR 是否固定两笔？后续新增 endpoint 如何收费？ | R13: 高 | S13: 在是否 own endpoint 上做总成本比较
... A29: POST-03 | B29: 开始跑交易后 | C29: License / Service / Network / Transaction Fees | D29: Transaction | E29: 待补费率 | F29: 是 | G29: 是 | H29: 否 | I29: Finance + Payments Ops | J29: 交易开始后 | K29: 0 | L29: 0 | M29: 0 | N29: =IF(OR(G29="否",H29="否"),0,L29) -> 0 | O29: =IF(OR(G29="否",H29="否"),0,M29) -> 0 | P29: 本 PDF 未展开，需另拉 Fee Schedule | Q29: 最新 Fee Schedule 明细能否单独拉表？ | R29: 高 | S29: 单独建立长期利润测算底表

Sheet 预算汇总
A1: 指标 | B1: 当前预算(USD) | C1: 压力预算(USD) | D1: 说明
A2: 一次性基线 | B2: =SUMIFS(预算清单!$N:$N,预算清单!$E:$E,"一次性基线") -> 113100 | C2: =SUMIFS(预算清单!$O:$O,预算清单!$E:$E,"一次性基线") -> 126100 | D2: License / Implementation / Testing / Access 等项目型成本
A3: 可选事件缓冲 | B3: =SUMIFS(预算清单!$N:$N,预算清单!$E:$E,"可选事件缓冲") -> 3500 | C3: =SUMIFS(预算清单!$O:$O,预算清单!$E:$E,"可选事件缓冲") -> 7000 | D3: 用于改期、取消、加急等缓冲
A4: 年化经常性 | B4: =SUMIFS(预算清单!$N:$N,预算清单!$E:$E,"年化经常性") -> 37400 | C4: =SUMIFS(预算清单!$O:$O,预算清单!$E:$E,"年化经常性") -> 37400 | D4: 按首年 run-rate 年化
A5: 待补费率 | B5: =SUMIFS(预算清单!$N:$N,预算清单!$E:$E,"待补费率") -> 0 | C5: =SUMIFS(预算清单!$O:$O,预算清单!$E:$E,"待补费率") -> 0 | D5: 交易级费率暂未纳入
A6: 总预算（不含待补费率） | B6: =SUM(B2:B4) -> 154000 | C6: =SUM(C2:C4) -> 170500 | D6: 当前最可执行预算口径
A7: 高风险已纳入预算 | B7: =SUMIFS(预算清单!$N:$N,预算清单!$R:$R,"高") -> 135000 | C7: =SUMIFS(预算清单!$O:$O,预算清单!$R:$R,"高") -> 145000 | D7: 优先盯防高风险项
A8: 未纳入预算的建议预算 | B8: =SUMIFS(预算清单!$L:$L,预算清单!$H:$H,"否") -> 153050 | C8: =SUMIFS(预算清单!$M:$M,预算清单!$H:$H,"否") -> 723800 | D8: 这些是潜在漏预算区
A10: 建议读法 | B10: 先看“总预算（不含待补费率）”把项目预算框住，再把“未纳入预算的建议预算”压小，最后单独补 transaction fee schedule。

Sheet 预算时间线
A1: 时间点 | B1: 节点 | C1: 预算重点 | D1: 对应费用 | E1: 管理动作
A2: T0 | B2: Licensing review kick-off | C2: 先锁最前置现金流 | D2: Initial Service Fee | E2: 立项时直接入预算
A3: T1 | B3: Provisional BID 批下 | C3: 记录宽限期时钟起点 | D3: Numeric Licensing Fee；Quarterly Minimum Fee 时钟 | E3: 确认 P-BID 生效日
A4: T2 | B4: Implementation kick-off | C4: 防止实施拖长吃预算 | D4: Project Management Fee | E4: 把月数写进里程碑
A5: T3 | B5: CIQ / 配置请求提交 | C5: 配置型一次性成本集中出现 | D5: Program Installation；各类证书费 | E5: 范围冻结后再提交
A6: T4 | B6: 测试准备与测试执行 | C6: 测试工具和人力成本混合爆发 | D6: VSTS；VTS；VCX；Attended Testing | E6: 一次排准测试，减少返工
A7: T5 | B7: Endpoint activation | C7: 自建 endpoint 大额接入费落地 | D7: Cloud Connect Access / EAS Installation | E7: 与第三方方案做总成本对比
A8: T6 | B8: BIN go-live | C8: 集中看前期开票与自动扣收 | D8: 多项 setup fee billing timing | E8: 做上线前 billing checklist
A9: T7 | B9: Go-live 后 | C9: 从项目支出切到运营支出 | D9: Visa Online；VROL；VCX；Maintenance | E9: 把 recurring fee 纳入 run-rate
A10: T8 | B10: 宽限期结束 | C10: 底座成本正式启动 | D10: Quarterly Minimum Fee | E10: 提前倒排季度账期
A11: T9 | B11: 长期运营 | C11: 看利润率而不是只看 setup fee | D11: Recurring fee + transaction-level fees | E11: 持续做 run-rate 与 margin 复盘
